{"total_count": 59, "results": [{"datetime": "2025-12-07T07:08:00+00:00", "resolutioncode": "PT1M", "quarterhour": "2025-12-07T07:00:00+00:00", "qualitystatus": "NotValidated", "ace": -9.038, "systemimbalance": -11.429, "alpha": 0.0, "alpha_prime": 0.0, "marginalincrementalprice": 80.935, "marginaldecrementalprice": 70.438, "imbalanceprice": 80.935}, {"datetime": "2025-12-07T07:09:00+00:00", "resolutioncode": "PT1M", "quarterhour": "2025-12-07T07:00:00+00:00", "qualitystatus": "NotValidated", "ace": -5.062, "systemimbalance": -13.567, "alpha": 0.0, "alpha_prime": 0.0, "marginalincrementalprice": 80.935, "marginaldecrementalprice": 70.35, "imbalanceprice": 80.935}, {"datetime": "2025-12-07T07:10:00+00:00", "resolutioncode": "PT1M", "quarterhour": "2025-12-07T07:00:00+00:00", "qualitystatus": "NotValidated", "ace": -2.576, "systemimbalance": -10.703, "alpha": 0.0, "alpha_prime": 0.0, "marginalincrementalprice": 80.935, "marginaldecrementalprice": 69.59, "imbalanceprice": 80.935}, {"datetime": "2025-12-07T07:11:00+00:00", "resolutioncode": "PT1M", "quarterhour": "2025-12-07T07:00:00+00:00", "qualitystatus": "NotValidated", "ace": -1.922, "systemimbalance": -6.445, "alpha": 0.0, "alpha_prime": 0.0, "marginalincrementalprice": 80.935, "marginaldecrementalprice": 68.804, "imbalanceprice": 80.935}, {"datetime": "2025-12-07T07:12:00+00:00", "resolutioncode": "PT1M", "quarterhour": "2025-12-07T07:00:00+00:00", "qualitystatus": "NotValidated", "ace": -1.801, "systemimbalance": -4.059, "alpha": 0.0, "alpha_prime": 0.0, "marginalincrementalprice": 80.935, "marginaldecrementalprice": 67.423, "imbalanceprice": 80.935}, {"datetime": "2025-12-07T07:13:00+00:00", "resolutioncode": "PT1M", "quarterhour": "2025-12-07T07:00:00+00:00", "qualitystatus": "NotValidated", "ace": -1.709, "systemimbalance": -0.349, "alpha": 0.0, "alpha_prime": 0.0, "marginalincrementalprice": 80.935, "marginaldecrementalprice": 65.321, "imbalanceprice": 80.935}, {"datetime": "2025-12-07T07:14:00+00:00", "resolutioncode": "PT1M", "quarterhour": "2025-12-07T07:00:00+00:00", "qualitystatus": "NotValidated", "ace": -1.539, "systemimbalance": 1.672, "alpha": 0.0, "alpha_prime": 0.0, "marginalincrementalprice": 90.57, "marginaldecrementalprice": 80.935, "imbalanceprice": 80.935}, {"datetime": "2025-12-07T07:15:00+00:00", "resolutioncode": "PT1M", "quarterhour": "2025-12-07T07:15:00+00:00", "qualitystatus": "DataIssue", "ace": 0.006, "systemimbalance": 25.496, "alpha": 0.0, "alpha_prime": 0.0, "marginalincrementalprice": 91.15, "marginaldecrementalprice": 30.854, "imbalanceprice": 30.854}, {"datetime": "2025-12-07T07:16:00+00:00", "resolutioncode": "PT1M", "quarterhour": "2025-12-07T07:15:00+00:00", "qualitystatus": "NotValidated", "ace": 0.125, "systemimbalance": 41.771, "alpha": 0.0, "alpha_prime": 0.0, "marginalincrementalprice": 91.15, "marginaldecrementalprice": 35.303, "imbalanceprice": 35.303}, {"datetime": "2025-12-07T07:17:00+00:00", "resolutioncode": "PT1M", "quarterhour": "2025-12-07T07:15:00+00:00", "qualitystatus": "NotValidated", "ace": 0.196, "systemimbalance": 41.258, "alpha": 0.0, "alpha_prime": 0.0, "marginalincrementalprice": 91.15, "marginaldecrementalprice": 34.748, "imbalanceprice": 34.748}, {"datetime": "2025-12-07T07:18:00+00:00", "resolutioncode": "PT1M", "quarterhour": "2025-12-07T07:15:00+00:00", "qualitystatus": "NotValidated", "ace": -0.052, "systemimbalance": 25.449, "alpha": 0.0, "alpha_prime": 0.0, "marginalincrementalprice": 91.15, "marginaldecrementalprice": 30.781, "imbalanceprice": 30.781}, {"datetime": "2025-12-07T07:19:00+00:00", "resolutioncode": "PT1M", "quarterhour": "2025-12-07T07:15:00+00:00", "qualitystatus": "NotValidated", "ace": -0.065, "systemimbalance": 8.091, "alpha": 0.0, "alpha_prime": 0.0, "marginalincrementalprice": 91.15, "marginaldecrementalprice": 81.225, "imbalanceprice": 81.225}, {"datetime": "2025-12-07T07:20:00+00:00", "resolutioncode": "PT1M", "quarterhour": "2025-12-07T07:15:00+00:00", "qualitystatus": "NotValidated", "ace": -0.046, "systemimbalance": 1.554, "alpha": 0.0, "alpha_prime": 0.0, "marginalincrementalprice": 91.15, "marginaldecrementalprice": 81.225, "imbalanceprice": 81.225}, {"datetime": "2025-12-07T07:21:00+00:00", "resolutioncode": "PT1M", "quarterhour": "2025-12-07T07:15:00+00:00", "qualitystatus": "NotValidated", "ace": -0.048, "systemimbalance": 1.288, "alpha": 0.0, "alpha_prime": 0.0, "marginalincrementalprice": 91.15, "marginaldecrementalprice": 81.225, "imbalanceprice": 81.225}, {"datetime": "2025-12-07T07:22:00+00:00", "resolutioncode": "PT1M", "quarterhour": "2025-12-07T07:15:00+00:00", "qualitystatus": "NotValidated", "ace": -0.031, "systemimbalance": 14.355, "alpha": 0.0, "alpha_prime": 0.0, "marginalincrementalprice": 91.15, "marginaldecrementalprice": 81.225, "imbalanceprice": 81.225}, {"datetime": "2025-12-07T07:23:00+00:00", "resolutioncode": "PT1M", "quarterhour": "2025-12-07T07:15:00+00:00", "qualitystatus": "NotValidated", "ace": 0.023, "systemimbalance": 28.119, "alpha": 0.0, "alpha_prime": 0.0, "marginalincrementalprice": 91.15, "marginaldecrementalprice": 28.408, "imbalanceprice": 28.408}, {"datetime": "2025-12-07T07:24:00+00:00", "resolutioncode": "PT1M", "quarterhour": "2025-12-07T07:15:00+00:00", "qualitystatus": "NotValidated", "ace": 0.021, "systemimbalance": 38.022, "alpha": 0.0, "alpha_prime": 0.0, "marginalincrementalprice": 91.15, "marginaldecrementalprice": 26.379, "imbalanceprice": 26.379}, {"datetime": "2025-12-07T07:25:00+00:00", "resolutioncode": "PT1M", "quarterhour": "2025-12-07T07:15:00+00:00", "qualitystatus": "NotValidated", "ace": 0.024, "systemimbalance": 34.918, "alpha": 0.0, "alpha_prime": 0.0, "marginalincrementalprice": 91.15, "marginaldecrementalprice": 25.514, "imbalanceprice": 25.514}, {"datetime": "2025-12-07T07:26:00+00:00", "resolutioncode": "PT1M", "quarterhour": "2025-12-07T07:15:00+00:00", "qualitystatus": "NotValidated", "ace": 0.023, "systemimbalance": 22.64, "alpha": 0.0, "alpha_prime": 0.0, "marginalincrementalprice": 91.15, "marginaldecrementalprice": 81.225, "imbalanceprice": 81.225}, {"datetime": "2025-12-07T07:27:00+00:00", "resolutioncode": "PT1M", "quarterhour": "2025-12-07T07:15:00+00:00", "qualitystatus": "NotValidated", "ace": -0.163, "systemimbalance": 6.256, "alpha": 0.0, "alpha_prime": 0.0, "marginalincrementalprice": 91.15, "marginaldecrementalprice": 81.225, "imbalanceprice": 81.225}, {"datetime": "2025-12-07T07:28:00+00:00", "resolutioncode": "PT1M", "quarterhour": "2025-12-07T07:15:00+00:00", "qualitystatus": "NotValidated", "ace": -0.152, "systemimbalance": -1.816, "alpha": 0.0, "alpha_prime": 0.0, "marginalincrementalprice": 81.225, "marginaldecrementalprice": 22.988, "imbalanceprice": 81.225}, {"datetime": "2025-12-07T07:29:00+00:00", "resolutioncode": "PT1M", "quarterhour": "2025-12-07T07:15:00+00:00", "qualitystatus": "NotValidated", "ace": -0.136, "systemimbalance": -0.4, "alpha": 0.0, "alpha_prime": 0.0, "marginalincrementalprice": 81.225, "marginaldecrementalprice": 22.547, "imbalanceprice": 81.225}, {"datetime": "2025-12-07T07:30:00+00:00", "resolutioncode": "PT1M", "quarterhour": "2025-12-07T07:30:00+00:00", "qualitystatus": "DataIssue", "ace": -0.003, "systemimbalance": 63.969, "alpha": 0.0, "alpha_prime": 0.0, "marginalincrementalprice": 95.66, "marginaldecrementalprice": 62.629, "imbalanceprice": 62.629}, {"datetime": "2025-12-07T07:31:00+00:00", "resolutioncode": "PT1M", "quarterhour": "2025-12-07T07:30:00+00:00", "qualitystatus": "NotValidated", "ace": -0.377, "systemimbalance": 6.372, "alpha": 0.0, "alpha_prime": 0.0, "marginalincrementalprice": 95.66, "marginaldecrementalprice": 84.78, "imbalanceprice": 84.78}, {"datetime": "2025-12-07T07:32:00+00:00", "resolutioncode": "PT1M", "quarterhour": "2025-12-07T07:30:00+00:00", "qualitystatus": "NotValidated", "ace": -2.56, "systemimbalance": -36.268, "alpha": 0.0, "alpha_prime": 0.0, "marginalincrementalprice": 95.66, "marginaldecrementalprice": 46.657, "imbalanceprice": 95.66}, {"datetime": "2025-12-07T07:33:00+00:00", "resolutioncode": "PT1M", "quarterhour": "2025-12-07T07:30:00+00:00", "qualitystatus": "NotValidated", "ace": -2.469, "systemimbalance": -37.903, "alpha": 0.0, "alpha_prime": 0.0, "marginalincrementalprice": 95.66, "marginaldecrementalprice": 50.651, "imbalanceprice": 95.66}, {"datetime": "2025-12-07T07:34:00+00:00", "resolutioncode": "PT1M", "quarterhour": "2025-12-07T07:30:00+00:00", "qualitystatus": "NotValidated", "ace": -1.299, "systemimbalance": -28.43, "alpha": 0.0, "alpha_prime": 0.0, "marginalincrementalprice": 95.66, "marginaldecrementalprice": 51.129, "imbalanceprice": 95.66}, {"datetime": "2025-12-07T07:35:00+00:00", "resolutioncode": "PT1M", "quarterhour": "2025-12-07T07:30:00+00:00", "qualitystatus": "NotValidated", "ace": 0.037, "systemimbalance": -28.096, "alpha": 0.0, "alpha_prime": 0.0, "marginalincrementalprice": 95.66, "marginaldecrementalprice": 53.84, "imbalanceprice": 95.66}, {"datetime": "2025-12-07T07:36:00+00:00", "resolutioncode": "PT1M", "quarterhour": "2025-12-07T07:30:00+00:00", "qualitystatus": "NotValidated", "ace": 0.537, "systemimbalance": -40.699, "alpha": 0.0, "alpha_prime": 0.0, "marginalincrementalprice": 95.66, "marginaldecrementalprice": 55.363, "imbalanceprice": 95.66}, {"datetime": "2025-12-07T07:37:00+00:00", "resolutioncode": "PT1M", "quarterhour": "2025-12-07T07:30:00+00:00", "qualitystatus": "NotValidated", "ace": 0.423, "systemimbalance": -50.97, "alpha": 0.0, "alpha_prime": 0.0, "marginalincrementalprice": 95.66, "marginaldecrementalprice": 51.95, "imbalanceprice": 95.66}, {"datetime": "2025-12-07T07:38:00+00:00", "resolutioncode": "PT1M", "quarterhour": "2025-12-07T07:30:00+00:00", "qualitystatus": "NotValidated", "ace": 0.468, "systemimbalance": -57.837, "alpha": 0.0, "alpha_prime": 0.0, "marginalincrementalprice": 95.66, "marginaldecrementalprice": 53.427, "imbalanceprice": 95.66}, {"datetime": "2025-12-07T07:39:00+00:00", "resolutioncode": "PT1M", "quarterhour": "2025-12-07T07:30:00+00:00", "qualitystatus": "NotValidated", "ace": 0.517, "systemimbalance": -62.308, "alpha": 0.0, "alpha_prime": 0.0, "marginalincrementalprice": 95.66, "marginaldecrementalprice": 54.666, "imbalanceprice": 95.66}, {"datetime": "2025-12-07T07:40:00+00:00", "resolutioncode": "PT1M", "quarterhour": "2025-12-07T07:30:00+00:00", "qualitystatus": "NotValidated", "ace": 0.464, "systemimbalance": -64.416, "alpha": 0.0, "alpha_prime": 0.0, "marginalincrementalprice": 95.66, "marginaldecrementalprice": 53.052, "imbalanceprice": 95.66}, {"datetime": "2025-12-07T07:41:00+00:00", "resolutioncode": "PT1M", "quarterhour": "2025-12-07T07:30:00+00:00", "qualitystatus": "NotValidated", "ace": 0.438, "systemimbalance": -67.575, "alpha": 0.0, "alpha_prime": 0.0, "marginalincrementalprice": 95.66, "marginaldecrementalprice": 52.412, "imbalanceprice": 95.66}, {"datetime": "2025-12-07T07:42:00+00:00", "resolutioncode": "PT1M", "quarterhour": "2025-12-07T07:30:00+00:00", "qualitystatus": "NotValidated", "ace": 0.421, "systemimbalance": -68.978, "alpha": 0.0, "alpha_prime": 0.0, "marginalincrementalprice": 95.66, "marginaldecrementalprice": 50.775, "imbalanceprice": 95.66}, {"datetime": "2025-12-07T07:43:00+00:00", "resolutioncode": "PT1M", "quarterhour": "2025-12-07T07:30:00+00:00", "qualitystatus": "NotValidated", "ace": 0.403, "systemimbalance": -68.344, "alpha": 0.0, "alpha_prime": 0.0, "marginalincrementalprice": 95.66, "marginaldecrementalprice": 50.238, "imbalanceprice": 95.66}, {"datetime": "2025-12-07T07:44:00+00:00", "resolutioncode": "PT1M", "quarterhour": "2025-12-07T07:30:00+00:00", "qualitystatus": "NotValidated", "ace": 0.373, "systemimbalance": -68.152, "alpha": 0.0, "alpha_prime": 0.0, "marginalincrementalprice": 95.66, "marginaldecrementalprice": 51.141, "imbalanceprice": 95.66}, {"datetime": "2025-12-07T07:45:00+00:00", "resolutioncode": "PT1M", "quarterhour": "2025-12-07T07:45:00+00:00", "qualitystatus": "DataIssue", "ace": 0.529, "systemimbalance": -92.583, "alpha": 0.0, "alpha_prime": 0.0, "marginalincrementalprice": 99.42, "marginaldecrementalprice": 60.869, "imbalanceprice": 99.42}, {"datetime": "2025-12-07T07:46:00+00:00", "resolutioncode": "PT1M", "quarterhour": "2025-12-07T07:45:00+00:00", "qualitystatus": "NotValidated", "ace": 0.531, "systemimbalance": -53.121, "alpha": 0.0, "alpha_prime": 0.0, "marginalincrementalprice": 99.42, "marginaldecrementalprice": 64.767, "imbalanceprice": 99.42}, {"datetime": "2025-12-07T07:47:00+00:00", "resolutioncode": "PT1M", "quarterhour": "2025-12-07T07:45:00+00:00", "qualitystatus": "NotValidated", "ace": 0.406, "systemimbalance": -40.289, "alpha": 0.0, "alpha_prime": 0.0, "marginalincrementalprice": 99.42, "marginaldecrementalprice": 67.963, "imbalanceprice": 99.42}, {"datetime": "2025-12-07T07:48:00+00:00", "resolutioncode": "PT1M", "quarterhour": "2025-12-07T07:45:00+00:00", "qualitystatus": "NotValidated", "ace": 0.441, "systemimbalance": -32.686, "alpha": 0.0, "alpha_prime": 0.0, "marginalincrementalprice": 99.42, "marginaldecrementalprice": 69.04, "imbalanceprice": 99.42}, {"datetime": "2025-12-07T07:49:00+00:00", "resolutioncode": "PT1M", "quarterhour": "2025-12-07T07:45:00+00:00", "qualitystatus": "NotValidated", "ace": 0.255, "systemimbalance": -44.371, "alpha": 0.0, "alpha_prime": 0.0, "marginalincrementalprice": 99.42, "marginaldecrementalprice": 67.195, "imbalanceprice": 99.42}, {"datetime": "2025-12-07T07:50:00+00:00", "resolutioncode": "PT1M", "quarterhour": "2025-12-07T07:45:00+00:00", "qualitystatus": "NotValidated", "ace": 0.299, "systemimbalance": -55.893, "alpha": 0.0, "alpha_prime": 0.0, "marginalincrementalprice": 99.42, "marginaldecrementalprice": 70.473, "imbalanceprice": 99.42}, {"datetime": "2025-12-07T07:51:00+00:00", "resolutioncode": "PT1M", "quarterhour": "2025-12-07T07:45:00+00:00", "qualitystatus": "NotValidated", "ace": 0.257, "systemimbalance": -65.514, "alpha": 0.0, "alpha_prime": 0.0, "marginalincrementalprice": 99.42, "marginaldecrementalprice": 73.9, "imbalanceprice": 99.42}, {"datetime": "2025-12-07T07:52:00+00:00", "resolutioncode": "PT1M", "quarterhour": "2025-12-07T07:45:00+00:00", "qualitystatus": "NotValidated", "ace": 0.331, "systemimbalance": -78.623, "alpha": 0.0, "alpha_prime": 0.0, "marginalincrementalprice": 99.42, "marginaldecrementalprice": 73.9, "imbalanceprice": 99.42}, {"datetime": "2025-12-07T07:53:00+00:00", "resolutioncode": "PT1M", "quarterhour": "2025-12-07T07:45:00+00:00", "qualitystatus": "NotValidated", "ace": 0.888, "systemimbalance": -94.0, "alpha": 0.0, "alpha_prime": 0.0, "marginalincrementalprice": 99.42, "marginaldecrementalprice": 73.706, "imbalanceprice": 99.42}, {"datetime": "2025-12-07T07:54:00+00:00", "resolutioncode": "PT1M", "quarterhour": "2025-12-07T07:45:00+00:00", "qualitystatus": "NotValidated", "ace": 1.165, "systemimbalance": -103.021, "alpha": 0.0, "alpha_prime": 0.0, "marginalincrementalprice": 99.42, "marginaldecrementalprice": 73.891, "imbalanceprice": 99.42}, {"datetime": "2025-12-07T07:55:00+00:00", "resolutioncode": "PT1M", "quarterhour": "2025-12-07T07:45:00+00:00", "qualitystatus": "NotValidated", "ace": 1.551, "systemimbalance": -110.574, "alpha": 0.0, "alpha_prime": 0.0, "marginalincrementalprice": 99.42, "marginaldecrementalprice": 73.9, "imbalanceprice": 99.42}, {"datetime": "2025-12-07T07:56:00+00:00", "resolutioncode": "PT1M", "quarterhour": "2025-12-07T07:45:00+00:00", "qualitystatus": "NotValidated", "ace": 1.495, "systemimbalance": -120.138, "alpha": 0.0, "alpha_prime": 0.0, "marginalincrementalprice": 99.42, "marginaldecrementalprice": 73.9, "imbalanceprice": 99.42}, {"datetime": "2025-12-07T07:57:00+00:00", "resolutioncode": "PT1M", "quarterhour": "2025-12-07T07:45:00+00:00", "qualitystatus": "NotValidated", "ace": 1.379, "systemimbalance": -132.363, "alpha": 0.0, "alpha_prime": 0.0, "marginalincrementalprice": 99.42, "marginaldecrementalprice": 73.9, "imbalanceprice": 99.42}, {"datetime": "2025-12-07T07:58:00+00:00", "resolutioncode": "PT1M", "quarterhour": "2025-12-07T07:45:00+00:00", "qualitystatus": "NotValidated", "ace": 1.076, "systemimbalance": -142.531, "alpha": 0.0, "alpha_prime": 0.0, "marginalincrementalprice": 99.42, "marginaldecrementalprice": 73.9, "imbalanceprice": 99.42}, {"datetime": "2025-12-07T07:59:00+00:00", "resolutioncode": "PT1M", "quarterhour": "2025-12-07T07:45:00+00:00", "qualitystatus": "NotValidated", "ace": 1.037, "systemimbalance": -143.148, "alpha": 0.0, "alpha_prime": 0.0, "marginalincrementalprice": 99.42, "marginaldecrementalprice": 73.9, "imbalanceprice": 99.42}, {"datetime": "2025-12-07T08:00:00+00:00", "resolutioncode": "PT1M", "quarterhour": "2025-12-07T08:00:00+00:00", "qualitystatus": "DataIssue", "ace": 7.842, "systemimbalance": 10.721, "alpha": 0.0, "alpha_prime": 0.0, "marginalincrementalprice": 92.91, "marginaldecrementalprice": 83.355, "imbalanceprice": 83.355}, {"datetime": "2025-12-07T08:01:00+00:00", "resolutioncode": "PT1M", "quarterhour": "2025-12-07T08:00:00+00:00", "qualitystatus": "NotValidated", "ace": 6.05, "systemimbalance": 53.561, "alpha": 0.0, "alpha_prime": 0.0, "marginalincrementalprice": 92.91, "marginaldecrementalprice": 72.201, "imbalanceprice": 72.201}, {"datetime": "2025-12-07T08:02:00+00:00", "resolutioncode": "PT1M", "quarterhour": "2025-12-07T08:00:00+00:00", "qualitystatus": "NotValidated", "ace": -4.082, "systemimbalance": 39.808, "alpha": 0.0, "alpha_prime": 0.0, "marginalincrementalprice": 92.91, "marginaldecrementalprice": 72.253, "imbalanceprice": 72.253}, {"datetime": "2025-12-07T08:03:00+00:00", "resolutioncode": "PT1M", "quarterhour": "2025-12-07T08:00:00+00:00", "qualitystatus": "NotValidated", "ace": -8.975, "systemimbalance": 15.459, "alpha": 0.0, "alpha_prime": 0.0, "marginalincrementalprice": 92.91, "marginaldecrementalprice": 83.355, "imbalanceprice": 83.355}, {"datetime": "2025-12-07T08:04:00+00:00", "resolutioncode": "PT1M", "quarterhour": "2025-12-07T08:00:00+00:00", "qualitystatus": "NotValidated", "ace": -10.806, "systemimbalance": -2.475, "alpha": 0.0, "alpha_prime": 0.0, "marginalincrementalprice": 83.355, "marginaldecrementalprice": 70.882, "imbalanceprice": 83.355}, {"datetime": "2025-12-07T08:05:00+00:00", "resolutioncode": "PT1M", "quarterhour": "2025-12-07T08:00:00+00:00", "qualitystatus": "NotValidated", "ace": -9.902, "systemimbalance": -27.885, "alpha": 0.0, "alpha_prime": 0.0, "marginalincrementalprice": 92.91, "marginaldecrementalprice": 73.8, "imbalanceprice": 92.91}, {"datetime": "2025-12-07T08:06:00+00:00", "resolutioncode": "PT1M", "quarterhour": "2025-12-07T08:00:00+00:00", "qualitystatus": "NotValidated", "ace": -9.562, "systemimbalance": -50.625, "alpha": 0.0, "alpha_prime": 0.0, "marginalincrementalprice": 92.91, "marginaldecrementalprice": 73.295, "imbalanceprice": 92.91}]}