{"total_count": 58, "results": [{"datetime": "2025-11-22T21:01:00+00:00", "resolutioncode": "PT1M", "quarterhour": "2025-11-22T21:00:00+00:00", "qualitystatus": "NotValidated", "ace": 62.409, "systemimbalance": 211.667, "alpha": 1.468, "alpha_prime": 0.0, "marginalincrementalprice": 95.7, "marginaldecrementalprice": 12.944, "imbalanceprice": 11.476}, {"datetime": "2025-11-22T21:02:00+00:00", "resolutioncode": "PT1M", "quarterhour": "2025-11-22T21:00:00+00:00", "qualitystatus": "NotValidated", "ace": 36.826, "systemimbalance": 172.136, "alpha": 1.085, "alpha_prime": 0.0, "marginalincrementalprice": 95.7, "marginaldecrementalprice": 19.93, "imbalanceprice": 18.845}, {"datetime": "2025-11-22T21:03:00+00:00", "resolutioncode": "PT1M", "quarterhour": "2025-11-22T21:00:00+00:00", "qualitystatus": "NotValidated", "ace": 12.894, "systemimbalance": 116.743, "alpha": 0.0, "alpha_prime": 0.0, "marginalincrementalprice": 95.7, "marginaldecrementalprice": 23.869, "imbalanceprice": 23.869}, {"datetime": "2025-11-22T21:04:00+00:00", "resolutioncode": "PT1M", "quarterhour": "2025-11-22T21:00:00+00:00", "qualitystatus": "NotValidated", "ace": 1.098, "systemimbalance": 66.328, "alpha": 0.0, "alpha_prime": 0.0, "marginalincrementalprice": 95.7, "marginaldecrementalprice": 36.502, "imbalanceprice": 36.502}, {"datetime": "2025-11-22T21:05:00+00:00", "resolutioncode": "PT1M", "quarterhour": "2025-11-22T21:00:00+00:00", "qualitystatus": "NotValidated", "ace": 2.872, "systemimbalance": 46.577, "alpha": 0.0, "alpha_prime": 0.0, "marginalincrementalprice": 95.7, "marginaldecrementalprice": 40.593, "imbalanceprice": 40.593}, {"datetime": "2025-11-22T21:06:00+00:00", "resolutioncode": "PT1M", "quarterhour": "2025-11-22T21:00:00+00:00", "qualitystatus": "NotValidated", "ace": 3.166, "systemimbalance": 32.645, "alpha": 0.0, "alpha_prime": 0.0, "marginalincrementalprice": 95.7, "marginaldecrementalprice": 43.557, "imbalanceprice": 43.557}, {"datetime": "2025-11-22T21:07:00+00:00", "resolutioncode": "PT1M", "quarterhour": "2025-11-22T21:00:00+00:00", "qualitystatus": "NotValidated", "ace": 0.759, "systemimbalance": 19.471, "alpha": 0.0, "alpha_prime": 0.0, "marginalincrementalprice": 95.7, "marginaldecrementalprice": 87.85, "imbalanceprice": 87.85}, {"datetime": "2025-11-22T21:08:00+00:00", "resolutioncode": "PT1M", "quarterhour": "2025-11-22T21:00:00+00:00", "qualitystatus": "NotValidated", "ace": -1.388, "systemimbalance": 12.528, "alpha": 0.0, "alpha_prime": 0.0, "marginalincrementalprice": 95.7, "marginaldecrementalprice": 87.85, "imbalanceprice": 87.85}, {"datetime": "2025-11-22T21:09:00+00:00", "resolutioncode": "PT1M", "quarterhour": "2025-11-22T21:00:00+00:00", "qualitystatus": "NotValidated", "ace": -0.596, "systemimbalance": 10.457, "alpha": 0.0, "alpha_prime": 0.0, "marginalincrementalprice": 95.7, "marginaldecrementalprice": 87.85, "imbalanceprice": 87.85}, {"datetime": "2025-11-22T21:10:00+00:00", "resolutioncode": "PT1M", "quarterhour": "2025-11-22T21:00:00+00:00", "qualitystatus": "NotValidated", "ace": 0.137, "systemimbalance": 12.447, "alpha": 0.0, "alpha_prime": 0.0, "marginalincrementalprice": 95.7, "marginaldecrementalprice": 87.85, "imbalanceprice": 87.85}, {"datetime": "2025-11-22T21:11:00+00:00", "resolutioncode": "PT1M", "quarterhour": "2025-11-22T21:00:00+00:00", "qualitystatus": "NotValidated", "ace": 0.105, "systemimbalance": 17.105, "alpha": 0.0, "alpha_prime": 0.0, "marginalincrementalprice": 95.7, "marginaldecrementalprice": 87.85, "imbalanceprice": 87.85}, {"datetime": "2025-11-22T21:12:00+00:00", "resolutioncode": "PT1M", "quarterhour": "2025-11-22T21:00:00+00:00", "qualitystatus": "NotValidated", "ace": 0.982, "systemimbalance": 20.738, "alpha": 0.0, "alpha_prime": 0.0, "marginalincrementalprice": 95.7, "marginaldecrementalprice": 87.85, "imbalanceprice": 87.85}, {"datetime": "2025-11-22T21:13:00+00:00", "resolutioncode": "PT1M", "quarterhour": "2025-11-22T21:00:00+00:00", "qualitystatus": "NotValidated", "ace": 0.944, "systemimbalance": 24.32, "alpha": 0.0, "alpha_prime": 0.0, "marginalincrementalprice": 95.7, "marginaldecrementalprice": 87.85, "imbalanceprice": 87.85}, {"datetime": "2025-11-22T21:14:00+00:00", "resolutioncode": "PT1M", "quarterhour": "2025-11-22T21:00:00+00:00", "qualitystatus": "NotValidated", "ace": 2.295, "systemimbalance": 29.761, "alpha": 0.0, "alpha_prime": 0.0, "marginalincrementalprice": 95.7, "marginaldecrementalprice": 55.911, "imbalanceprice": 55.911}, {"datetime": "2025-11-22T21:15:00+00:00", "resolutioncode": "PT1M", "quarterhour": "2025-11-22T21:15:00+00:00", "qualitystatus": "DataIssue", "ace": 5.677, "systemimbalance": 76.976, "alpha": 0.0, "alpha_prime": 0.0, "marginalincrementalprice": 97.67, "marginaldecrementalprice": 57.974, "imbalanceprice": 57.974}, {"datetime": "2025-11-22T21:16:00+00:00", "resolutioncode": "PT1M", "quarterhour": "2025-11-22T21:15:00+00:00", "qualitystatus": "NotValidated", "ace": 4.26, "systemimbalance": 72.706, "alpha": 0.0, "alpha_prime": 0.0, "marginalincrementalprice": 97.67, "marginaldecrementalprice": 59.745, "imbalanceprice": 59.745}, {"datetime": "2025-11-22T21:17:00+00:00", "resolutioncode": "PT1M", "quarterhour": "2025-11-22T21:15:00+00:00", "qualitystatus": "NotValidated", "ace": 2.081, "systemimbalance": 57.567, "alpha": 0.0, "alpha_prime": 0.0, "marginalincrementalprice": 97.67, "marginaldecrementalprice": 60.957, "imbalanceprice": 60.957}, {"datetime": "2025-11-22T21:18:00+00:00", "resolutioncode": "PT1M", "quarterhour": "2025-11-22T21:15:00+00:00", "qualitystatus": "NotValidated", "ace": 0.735, "systemimbalance": 38.75, "alpha": 0.0, "alpha_prime": 0.0, "marginalincrementalprice": 97.67, "marginaldecrementalprice": 62.819, "imbalanceprice": 62.819}, {"datetime": "2025-11-22T21:19:00+00:00", "resolutioncode": "PT1M", "quarterhour": "2025-11-22T21:15:00+00:00", "qualitystatus": "NotValidated", "ace": 0.919, "systemimbalance": 36.322, "alpha": 0.0, "alpha_prime": 0.0, "marginalincrementalprice": 97.67, "marginaldecrementalprice": 64.107, "imbalanceprice": 64.107}, {"datetime": "2025-11-22T21:20:00+00:00", "resolutioncode": "PT1M", "quarterhour": "2025-11-22T21:15:00+00:00", "qualitystatus": "NotValidated", "ace": 0.365, "systemimbalance": 32.161, "alpha": 0.0, "alpha_prime": 0.0, "marginalincrementalprice": 97.67, "marginaldecrementalprice": 64.668, "imbalanceprice": 64.668}, {"datetime": "2025-11-22T21:21:00+00:00", "resolutioncode": "PT1M", "quarterhour": "2025-11-22T21:15:00+00:00", "qualitystatus": "NotValidated", "ace": -0.194, "systemimbalance": 23.18, "alpha": 0.0, "alpha_prime": 0.0, "marginalincrementalprice": 97.67, "marginaldecrementalprice": 84.335, "imbalanceprice": 84.335}, {"datetime": "2025-11-22T21:22:00+00:00", "resolutioncode": "PT1M", "quarterhour": "2025-11-22T21:15:00+00:00", "qualitystatus": "NotValidated", "ace": -0.006, "systemimbalance": 20.252, "alpha": 0.0, "alpha_prime": 0.0, "marginalincrementalprice": 97.67, "marginaldecrementalprice": 84.335, "imbalanceprice": 84.335}, {"datetime": "2025-11-22T21:23:00+00:00", "resolutioncode": "PT1M", "quarterhour": "2025-11-22T21:15:00+00:00", "qualitystatus": "DataIssue", "ace": 0.323, "systemimbalance": 18.48, "alpha": 0.0, "alpha_prime": 0.0, "marginalincrementalprice": 97.67, "marginaldecrementalprice": 84.335, "imbalanceprice": 84.335}, {"datetime": "2025-11-22T21:24:00+00:00", "resolutioncode": "PT1M", "quarterhour": "2025-11-22T21:15:00+00:00", "qualitystatus": "DataIssue", "ace": 0.728, "systemimbalance": 21.733, "alpha": 0.0, "alpha_prime": 0.0, "marginalincrementalprice": 97.67, "marginaldecrementalprice": 84.335, "imbalanceprice": 84.335}, {"datetime": "2025-11-22T21:25:00+00:00", "resolutioncode": "PT1M", "quarterhour": "2025-11-22T21:15:00+00:00", "qualitystatus": "DataIssue", "ace": 1.419, "systemimbalance": 28.211, "alpha": 0.0, "alpha_prime": 0.0, "marginalincrementalprice": 97.67, "marginaldecrementalprice": 69.999, "imbalanceprice": 69.999}, {"datetime": "2025-11-22T21:26:00+00:00", "resolutioncode": "PT1M", "quarterhour": "2025-11-22T21:15:00+00:00", "qualitystatus": "DataIssue", "ace": 3.173, "systemimbalance": 35.936, "alpha": 0.0, "alpha_prime": 0.0, "marginalincrementalprice": 97.67, "marginaldecrementalprice": 66.403, "imbalanceprice": 66.403}, {"datetime": "2025-11-22T21:27:00+00:00", "resolutioncode": "PT1M", "quarterhour": "2025-11-22T21:15:00+00:00", "qualitystatus": "DataIssue", "ace": 4.235, "systemimbalance": 37.649, "alpha": 0.0, "alpha_prime": 0.0, "marginalincrementalprice": 97.67, "marginaldecrementalprice": 67.56, "imbalanceprice": 67.56}, {"datetime": "2025-11-22T21:28:00+00:00", "resolutioncode": "PT1M", "quarterhour": "2025-11-22T21:15:00+00:00", "qualitystatus": "DataIssue", "ace": 4.136, "systemimbalance": 36.516, "alpha": 0.0, "alpha_prime": 0.0, "marginalincrementalprice": 97.67, "marginaldecrementalprice": 68.391, "imbalanceprice": 68.391}, {"datetime": "2025-11-22T21:29:00+00:00", "resolutioncode": "PT1M", "quarterhour": "2025-11-22T21:15:00+00:00", "qualitystatus": "DataIssue", "ace": 3.952, "systemimbalance": 30.365, "alpha": 0.0, "alpha_prime": 0.0, "marginalincrementalprice": 97.67, "marginaldecrementalprice": 68.651, "imbalanceprice": 68.651}, {"datetime": "2025-11-22T21:30:00+00:00", "resolutioncode": "PT1M", "quarterhour": "2025-11-22T21:30:00+00:00", "qualitystatus": "DataIssue", "ace": 0.903, "systemimbalance": -15.894, "alpha": 0.0, "alpha_prime": 0.0, "marginalincrementalprice": 89.455, "marginaldecrementalprice": 77.0, "imbalanceprice": 89.455}, {"datetime": "2025-11-22T21:31:00+00:00", "resolutioncode": "PT1M", "quarterhour": "2025-11-22T21:30:00+00:00", "qualitystatus": "DataIssue", "ace": -0.728, "systemimbalance": -22.248, "alpha": 0.0, "alpha_prime": 0.0, "marginalincrementalprice": 89.455, "marginaldecrementalprice": 77.0, "imbalanceprice": 89.455}, {"datetime": "2025-11-22T21:32:00+00:00", "resolutioncode": "PT1M", "quarterhour": "2025-11-22T21:30:00+00:00", "qualitystatus": "DataIssue", "ace": -0.891, "systemimbalance": -32.564, "alpha": 0.0, "alpha_prime": 0.0, "marginalincrementalprice": 109.637, "marginaldecrementalprice": 77.0, "imbalanceprice": 109.637}, {"datetime": "2025-11-22T21:33:00+00:00", "resolutioncode": "PT1M", "quarterhour": "2025-11-22T21:30:00+00:00", "qualitystatus": "DataIssue", "ace": -0.884, "systemimbalance": -40.741, "alpha": 0.0, "alpha_prime": 0.0, "marginalincrementalprice": 112.871, "marginaldecrementalprice": 77.0, "imbalanceprice": 112.871}, {"datetime": "2025-11-22T21:34:00+00:00", "resolutioncode": "PT1M", "quarterhour": "2025-11-22T21:30:00+00:00", "qualitystatus": "DataIssue", "ace": 11.51, "systemimbalance": -18.986, "alpha": 0.0, "alpha_prime": 0.0, "marginalincrementalprice": 89.455, "marginaldecrementalprice": 77.0, "imbalanceprice": 89.455}, {"datetime": "2025-11-22T21:35:00+00:00", "resolutioncode": "PT1M", "quarterhour": "2025-11-22T21:30:00+00:00", "qualitystatus": "DataIssue", "ace": 20.605, "systemimbalance": -3.396, "alpha": 0.0, "alpha_prime": 0.0, "marginalincrementalprice": 89.455, "marginaldecrementalprice": 77.0, "imbalanceprice": 89.455}, {"datetime": "2025-11-22T21:36:00+00:00", "resolutioncode": "PT1M", "quarterhour": "2025-11-22T21:30:00+00:00", "qualitystatus": "DataIssue", "ace": 29.188, "systemimbalance": 12.676, "alpha": 0.0, "alpha_prime": 0.0, "marginalincrementalprice": 101.91, "marginaldecrementalprice": 89.455, "imbalanceprice": 89.455}, {"datetime": "2025-11-22T21:37:00+00:00", "resolutioncode": "PT1M", "quarterhour": "2025-11-22T21:30:00+00:00", "qualitystatus": "DataIssue", "ace": 25.824, "systemimbalance": 15.389, "alpha": 0.0, "alpha_prime": 0.0, "marginalincrementalprice": 101.91, "marginaldecrementalprice": 89.455, "imbalanceprice": 89.455}, {"datetime": "2025-11-22T21:38:00+00:00", "resolutioncode": "PT1M", "quarterhour": "2025-11-22T21:30:00+00:00", "qualitystatus": "DataIssue", "ace": 19.757, "systemimbalance": 12.412, "alpha": 0.0, "alpha_prime": 0.0, "marginalincrementalprice": 101.91, "marginaldecrementalprice": 89.455, "imbalanceprice": 89.455}, {"datetime": "2025-11-22T21:39:00+00:00", "resolutioncode": "PT1M", "quarterhour": "2025-11-22T21:30:00+00:00", "qualitystatus": "DataIssue", "ace": 18.537, "systemimbalance": 12.074, "alpha": 0.0, "alpha_prime": 0.0, "marginalincrementalprice": 101.91, "marginaldecrementalprice": 89.455, "imbalanceprice": 89.455}, {"datetime": "2025-11-22T21:40:00+00:00", "resolutioncode": "PT1M", "quarterhour": "2025-11-22T21:30:00+00:00", "qualitystatus": "DataIssue", "ace": 19.03, "systemimbalance": 13.491, "alpha": 0.0, "alpha_prime": 0.0, "marginalincrementalprice": 101.91, "marginaldecrementalprice": 89.455, "imbalanceprice": 89.455}, {"datetime": "2025-11-22T21:41:00+00:00", "resolutioncode": "PT1M", "quarterhour": "2025-11-22T21:30:00+00:00", "qualitystatus": "DataIssue", "ace": 17.682, "systemimbalance": 12.369, "alpha": 0.0, "alpha_prime": 0.0, "marginalincrementalprice": 101.91, "marginaldecrementalprice": 89.455, "imbalanceprice": 89.455}, {"datetime": "2025-11-22T21:42:00+00:00", "resolutioncode": "PT1M", "quarterhour": "2025-11-22T21:30:00+00:00", "qualitystatus": "DataIssue", "ace": 16.61, "systemimbalance": 10.552, "alpha": 0.0, "alpha_prime": 0.0, "marginalincrementalprice": 101.91, "marginaldecrementalprice": 89.455, "imbalanceprice": 89.455}, {"datetime": "2025-11-22T21:43:00+00:00", "resolutioncode": "PT1M", "quarterhour": "2025-11-22T21:30:00+00:00", "qualitystatus": "DataIssue", "ace": 20.32, "systemimbalance": 15.385, "alpha": 0.0, "alpha_prime": 0.0, "marginalincrementalprice": 101.91, "marginaldecrementalprice": 89.455, "imbalanceprice": 89.455}, {"datetime": "2025-11-22T21:44:00+00:00", "resolutioncode": "PT1M", "quarterhour": "2025-11-22T21:30:00+00:00", "qualitystatus": "DataIssue", "ace": 26.083, "systemimbalance": 22.862, "alpha": 0.0, "alpha_prime": 0.0, "marginalincrementalprice": 101.91, "marginaldecrementalprice": 89.455, "imbalanceprice": 89.455}, {"datetime": "2025-11-22T21:45:00+00:00", "resolutioncode": "PT1M", "quarterhour": "2025-11-22T21:45:00+00:00", "qualitystatus": "DataIssue", "ace": 121.49, "systemimbalance": 146.439, "alpha": 0.0, "alpha_prime": 0.0, "marginalincrementalprice": 100.25, "marginaldecrementalprice": 54.855, "imbalanceprice": 54.855}, {"datetime": "2025-11-22T21:46:00+00:00", "resolutioncode": "PT1M", "quarterhour": "2025-11-22T21:45:00+00:00", "qualitystatus": "NotValidated", "ace": 120.73, "systemimbalance": 157.98, "alpha": 0.789, "alpha_prime": 0.0, "marginalincrementalprice": 100.25, "marginaldecrementalprice": 54.923, "imbalanceprice": 54.134}, {"datetime": "2025-11-22T21:47:00+00:00", "resolutioncode": "PT1M", "quarterhour": "2025-11-22T21:45:00+00:00", "qualitystatus": "NotValidated", "ace": 107.987, "systemimbalance": 157.174, "alpha": 0.784, "alpha_prime": 0.0, "marginalincrementalprice": 100.25, "marginaldecrementalprice": 54.572, "imbalanceprice": 53.788}, {"datetime": "2025-11-22T21:48:00+00:00", "resolutioncode": "PT1M", "quarterhour": "2025-11-22T21:45:00+00:00", "qualitystatus": "NotValidated", "ace": 89.758, "systemimbalance": 150.432, "alpha": 0.744, "alpha_prime": 0.0, "marginalincrementalprice": 100.25, "marginaldecrementalprice": 54.738, "imbalanceprice": 53.994}, {"datetime": "2025-11-22T21:49:00+00:00", "resolutioncode": "PT1M", "quarterhour": "2025-11-22T21:45:00+00:00", "qualitystatus": "NotValidated", "ace": 52.405, "systemimbalance": 115.184, "alpha": 0.0, "alpha_prime": 0.0, "marginalincrementalprice": 100.25, "marginaldecrementalprice": 56.021, "imbalanceprice": 56.021}, {"datetime": "2025-11-22T21:50:00+00:00", "resolutioncode": "PT1M", "quarterhour": "2025-11-22T21:45:00+00:00", "qualitystatus": "NotValidated", "ace": 36.632, "systemimbalance": 100.945, "alpha": 0.0, "alpha_prime": 0.0, "marginalincrementalprice": 100.25, "marginaldecrementalprice": 57.113, "imbalanceprice": 57.113}, {"datetime": "2025-11-22T21:51:00+00:00", "resolutioncode": "PT1M", "quarterhour": "2025-11-22T21:45:00+00:00", "qualitystatus": "NotValidated", "ace": 28.149, "systemimbalance": 81.727, "alpha": 0.0, "alpha_prime": 0.0, "marginalincrementalprice": 100.25, "marginaldecrementalprice": 61.074, "imbalanceprice": 61.074}, {"datetime": "2025-11-22T21:52:00+00:00", "resolutioncode": "PT1M", "quarterhour": "2025-11-22T21:45:00+00:00", "qualitystatus": "NotValidated", "ace": 26.81, "systemimbalance": 72.722, "alpha": 0.0, "alpha_prime": 0.0, "marginalincrementalprice": 100.25, "marginaldecrementalprice": 62.174, "imbalanceprice": 62.174}, {"datetime": "2025-11-22T21:53:00+00:00", "resolutioncode": "PT1M", "quarterhour": "2025-11-22T21:45:00+00:00", "qualitystatus": "NotValidated", "ace": 24.2, "systemimbalance": 65.988, "alpha": 0.0, "alpha_prime": 0.0, "marginalincrementalprice": 100.25, "marginaldecrementalprice": 63.018, "imbalanceprice": 63.018}, {"datetime": "2025-11-22T21:54:00+00:00", "resolutioncode": "PT1M", "quarterhour": "2025-11-22T21:45:00+00:00", "qualitystatus": "NotValidated", "ace": 22.794, "systemimbalance": 59.408, "alpha": 0.0, "alpha_prime": 0.0, "marginalincrementalprice": 100.25, "marginaldecrementalprice": 63.571, "imbalanceprice": 63.571}, {"datetime": "2025-11-22T21:55:00+00:00", "resolutioncode": "PT1M", "quarterhour": "2025-11-22T21:45:00+00:00", "qualitystatus": "NotValidated", "ace": 23.514, "systemimbalance": 58.193, "alpha": 0.0, "alpha_prime": 0.0, "marginalincrementalprice": 100.25, "marginaldecrementalprice": 63.274, "imbalanceprice": 63.274}, {"datetime": "2025-11-22T21:56:00+00:00", "resolutioncode": "PT1M", "quarterhour": "2025-11-22T21:45:00+00:00", "qualitystatus": "NotValidated", "ace": 26.772, "systemimbalance": 62.821, "alpha": 0.0, "alpha_prime": 0.0, "marginalincrementalprice": 100.25, "marginaldecrementalprice": 62.204, "imbalanceprice": 62.204}, {"datetime": "2025-11-22T21:57:00+00:00", "resolutioncode": "PT1M", "quarterhour": "2025-11-22T21:45:00+00:00", "qualitystatus": "NotValidated", "ace": 28.797, "systemimbalance": 65.953, "alpha": 0.0, "alpha_prime": 0.0, "marginalincrementalprice": 100.25, "marginaldecrementalprice": 61.001, "imbalanceprice": 61.001}, {"datetime": "2025-11-22T21:58:00+00:00", "resolutioncode": "PT1M", "quarterhour": "2025-11-22T21:45:00+00:00", "qualitystatus": "NotValidated", "ace": 28.136, "systemimbalance": 67.21, "alpha": 0.0, "alpha_prime": 0.0, "marginalincrementalprice": 100.25, "marginaldecrementalprice": 60.646, "imbalanceprice": 60.646}]}