{"total_count": 58, "results": [{"datetime": "2025-11-23T01:01:00+00:00", "resolutioncode": "PT1M", "quarterhour": "2025-11-23T01:00:00+00:00", "qualitystatus": "NotValidated", "ace": 1.757, "systemimbalance": -5.451, "alpha": 0.0, "alpha_prime": 0.0, "marginalincrementalprice": 93.45, "marginaldecrementalprice": 86.967, "imbalanceprice": 93.45}, {"datetime": "2025-11-23T01:02:00+00:00", "resolutioncode": "PT1M", "quarterhour": "2025-11-23T01:00:00+00:00", "qualitystatus": "NotValidated", "ace": 1.151, "systemimbalance": 5.801, "alpha": 0.0, "alpha_prime": 0.0, "marginalincrementalprice": 94.9, "marginaldecrementalprice": 93.45, "imbalanceprice": 93.45}, {"datetime": "2025-11-23T01:03:00+00:00", "resolutioncode": "PT1M", "quarterhour": "2025-11-23T01:00:00+00:00", "qualitystatus": "NotValidated", "ace": 0.054, "systemimbalance": -5.91, "alpha": 0.0, "alpha_prime": 0.0, "marginalincrementalprice": 93.45, "marginaldecrementalprice": 82.85, "imbalanceprice": 93.45}, {"datetime": "2025-11-23T01:04:00+00:00", "resolutioncode": "PT1M", "quarterhour": "2025-11-23T01:00:00+00:00", "qualitystatus": "NotValidated", "ace": 0.647, "systemimbalance": -21.094, "alpha": 0.0, "alpha_prime": 0.0, "marginalincrementalprice": 93.45, "marginaldecrementalprice": 81.653, "imbalanceprice": 93.45}, {"datetime": "2025-11-23T01:05:00+00:00", "resolutioncode": "PT1M", "quarterhour": "2025-11-23T01:00:00+00:00", "qualitystatus": "NotValidated", "ace": -0.217, "systemimbalance": -38.604, "alpha": 0.0, "alpha_prime": 0.0, "marginalincrementalprice": 94.9, "marginaldecrementalprice": 82.28, "imbalanceprice": 94.9}, {"datetime": "2025-11-23T01:06:00+00:00", "resolutioncode": "PT1M", "quarterhour": "2025-11-23T01:00:00+00:00", "qualitystatus": "NotValidated", "ace": -2.281, "systemimbalance": -50.64, "alpha": 0.0, "alpha_prime": 0.0, "marginalincrementalprice": 94.9, "marginaldecrementalprice": 84.235, "imbalanceprice": 94.9}, {"datetime": "2025-11-23T01:07:00+00:00", "resolutioncode": "PT1M", "quarterhour": "2025-11-23T01:00:00+00:00", "qualitystatus": "NotValidated", "ace": -11.476, "systemimbalance": -67.696, "alpha": 0.0, "alpha_prime": 0.0, "marginalincrementalprice": 94.9, "marginaldecrementalprice": 89.103, "imbalanceprice": 94.9}, {"datetime": "2025-11-23T01:08:00+00:00", "resolutioncode": "PT1M", "quarterhour": "2025-11-23T01:00:00+00:00", "qualitystatus": "NotValidated", "ace": -12.831, "systemimbalance": -75.051, "alpha": 0.0, "alpha_prime": 0.0, "marginalincrementalprice": 94.9, "marginaldecrementalprice": 90.42, "imbalanceprice": 94.9}, {"datetime": "2025-11-23T01:09:00+00:00", "resolutioncode": "PT1M", "quarterhour": "2025-11-23T01:00:00+00:00", "qualitystatus": "NotValidated", "ace": -12.467, "systemimbalance": -77.835, "alpha": 0.0, "alpha_prime": 0.0, "marginalincrementalprice": 94.9, "marginaldecrementalprice": 91.497, "imbalanceprice": 94.9}, {"datetime": "2025-11-23T01:10:00+00:00", "resolutioncode": "PT1M", "quarterhour": "2025-11-23T01:00:00+00:00", "qualitystatus": "NotValidated", "ace": -13.803, "systemimbalance": -80.72, "alpha": 0.0, "alpha_prime": 0.0, "marginalincrementalprice": 94.9, "marginaldecrementalprice": 92.0, "imbalanceprice": 94.9}, {"datetime": "2025-11-23T01:11:00+00:00", "resolutioncode": "PT1M", "quarterhour": "2025-11-23T01:00:00+00:00", "qualitystatus": "NotValidated", "ace": -10.778, "systemimbalance": -78.361, "alpha": 0.0, "alpha_prime": 0.0, "marginalincrementalprice": 94.9, "marginaldecrementalprice": 92.0, "imbalanceprice": 94.9}, {"datetime": "2025-11-23T01:12:00+00:00", "resolutioncode": "PT1M", "quarterhour": "2025-11-23T01:00:00+00:00", "qualitystatus": "NotValidated", "ace": -7.536, "systemimbalance": -75.647, "alpha": 0.0, "alpha_prime": 0.0, "marginalincrementalprice": 94.9, "marginaldecrementalprice": 92.0, "imbalanceprice": 94.9}, {"datetime": "2025-11-23T01:13:00+00:00", "resolutioncode": "PT1M", "quarterhour": "2025-11-23T01:00:00+00:00", "qualitystatus": "NotValidated", "ace": -5.744, "systemimbalance": -73.18, "alpha": 0.0, "alpha_prime": 0.0, "marginalincrementalprice": 94.9, "marginaldecrementalprice": 92.0, "imbalanceprice": 94.9}, {"datetime": "2025-11-23T01:14:00+00:00", "resolutioncode": "PT1M", "quarterhour": "2025-11-23T01:00:00+00:00", "qualitystatus": "NotValidated", "ace": -5.39, "systemimbalance": -69.616, "alpha": 0.0, "alpha_prime": 0.0, "marginalincrementalprice": 94.9, "marginaldecrementalprice": 92.0, "imbalanceprice": 94.9}, {"datetime": "2025-11-23T01:15:00+00:00", "resolutioncode": "PT1M", "quarterhour": "2025-11-23T01:15:00+00:00", "qualitystatus": "DataIssue", "ace": -10.855, "systemimbalance": -71.499, "alpha": 0.0, "alpha_prime": 0.0, "marginalincrementalprice": 95.319, "marginaldecrementalprice": 92.0, "imbalanceprice": 95.319}, {"datetime": "2025-11-23T01:16:00+00:00", "resolutioncode": "PT1M", "quarterhour": "2025-11-23T01:15:00+00:00", "qualitystatus": "NotValidated", "ace": -23.125, "systemimbalance": -92.574, "alpha": 0.0, "alpha_prime": 0.0, "marginalincrementalprice": 97.359, "marginaldecrementalprice": 92.0, "imbalanceprice": 97.359}, {"datetime": "2025-11-23T01:17:00+00:00", "resolutioncode": "PT1M", "quarterhour": "2025-11-23T01:15:00+00:00", "qualitystatus": "NotValidated", "ace": -21.78, "systemimbalance": -85.952, "alpha": 0.0, "alpha_prime": 0.0, "marginalincrementalprice": 96.379, "marginaldecrementalprice": 92.0, "imbalanceprice": 96.379}, {"datetime": "2025-11-23T01:18:00+00:00", "resolutioncode": "PT1M", "quarterhour": "2025-11-23T01:15:00+00:00", "qualitystatus": "NotValidated", "ace": -12.757, "systemimbalance": -82.356, "alpha": 0.0, "alpha_prime": 0.0, "marginalincrementalprice": 95.044, "marginaldecrementalprice": 92.0, "imbalanceprice": 95.044}, {"datetime": "2025-11-23T01:19:00+00:00", "resolutioncode": "PT1M", "quarterhour": "2025-11-23T01:15:00+00:00", "qualitystatus": "NotValidated", "ace": -9.521, "systemimbalance": -80.799, "alpha": 0.0, "alpha_prime": 0.0, "marginalincrementalprice": 95.0, "marginaldecrementalprice": 91.79, "imbalanceprice": 95.0}, {"datetime": "2025-11-23T01:20:00+00:00", "resolutioncode": "PT1M", "quarterhour": "2025-11-23T01:15:00+00:00", "qualitystatus": "NotValidated", "ace": -7.603, "systemimbalance": -77.38, "alpha": 0.0, "alpha_prime": 0.0, "marginalincrementalprice": 95.0, "marginaldecrementalprice": 90.908, "imbalanceprice": 95.0}, {"datetime": "2025-11-23T01:21:00+00:00", "resolutioncode": "PT1M", "quarterhour": "2025-11-23T01:15:00+00:00", "qualitystatus": "NotValidated", "ace": -6.036, "systemimbalance": -78.464, "alpha": 0.0, "alpha_prime": 0.0, "marginalincrementalprice": 95.0, "marginaldecrementalprice": 87.177, "imbalanceprice": 95.0}, {"datetime": "2025-11-23T01:22:00+00:00", "resolutioncode": "PT1M", "quarterhour": "2025-11-23T01:15:00+00:00", "qualitystatus": "NotValidated", "ace": -4.768, "systemimbalance": -79.048, "alpha": 0.0, "alpha_prime": 0.0, "marginalincrementalprice": 95.0, "marginaldecrementalprice": 81.563, "imbalanceprice": 95.0}, {"datetime": "2025-11-23T01:23:00+00:00", "resolutioncode": "PT1M", "quarterhour": "2025-11-23T01:15:00+00:00", "qualitystatus": "NotValidated", "ace": -4.169, "systemimbalance": -77.697, "alpha": 0.0, "alpha_prime": 0.0, "marginalincrementalprice": 95.0, "marginaldecrementalprice": 79.397, "imbalanceprice": 95.0}, {"datetime": "2025-11-23T01:24:00+00:00", "resolutioncode": "PT1M", "quarterhour": "2025-11-23T01:15:00+00:00", "qualitystatus": "NotValidated", "ace": -3.756, "systemimbalance": -77.002, "alpha": 0.0, "alpha_prime": 0.0, "marginalincrementalprice": 95.0, "marginaldecrementalprice": 78.548, "imbalanceprice": 95.0}, {"datetime": "2025-11-23T01:25:00+00:00", "resolutioncode": "PT1M", "quarterhour": "2025-11-23T01:15:00+00:00", "qualitystatus": "NotValidated", "ace": -3.367, "systemimbalance": -73.2, "alpha": 0.0, "alpha_prime": 0.0, "marginalincrementalprice": 95.0, "marginaldecrementalprice": 77.923, "imbalanceprice": 95.0}, {"datetime": "2025-11-23T01:26:00+00:00", "resolutioncode": "PT1M", "quarterhour": "2025-11-23T01:15:00+00:00", "qualitystatus": "NotValidated", "ace": -3.23, "systemimbalance": -69.148, "alpha": 0.0, "alpha_prime": 0.0, "marginalincrementalprice": 95.0, "marginaldecrementalprice": 77.497, "imbalanceprice": 95.0}, {"datetime": "2025-11-23T01:27:00+00:00", "resolutioncode": "PT1M", "quarterhour": "2025-11-23T01:15:00+00:00", "qualitystatus": "NotValidated", "ace": -2.768, "systemimbalance": -64.069, "alpha": 0.0, "alpha_prime": 0.0, "marginalincrementalprice": 95.0, "marginaldecrementalprice": 77.456, "imbalanceprice": 95.0}, {"datetime": "2025-11-23T01:28:00+00:00", "resolutioncode": "PT1M", "quarterhour": "2025-11-23T01:15:00+00:00", "qualitystatus": "NotValidated", "ace": -3.353, "systemimbalance": -58.559, "alpha": 0.0, "alpha_prime": 0.0, "marginalincrementalprice": 95.0, "marginaldecrementalprice": 76.993, "imbalanceprice": 95.0}, {"datetime": "2025-11-23T01:29:00+00:00", "resolutioncode": "PT1M", "quarterhour": "2025-11-23T01:15:00+00:00", "qualitystatus": "NotValidated", "ace": -5.225, "systemimbalance": -54.237, "alpha": 0.0, "alpha_prime": 0.0, "marginalincrementalprice": 95.0, "marginaldecrementalprice": 76.615, "imbalanceprice": 95.0}, {"datetime": "2025-11-23T01:30:00+00:00", "resolutioncode": "PT1M", "quarterhour": "2025-11-23T01:30:00+00:00", "qualitystatus": "DataIssue", "ace": -2.707, "systemimbalance": -5.605, "alpha": 0.0, "alpha_prime": 0.0, "marginalincrementalprice": 93.545, "marginaldecrementalprice": 66.033, "imbalanceprice": 93.545}, {"datetime": "2025-11-23T01:31:00+00:00", "resolutioncode": "PT1M", "quarterhour": "2025-11-23T01:30:00+00:00", "qualitystatus": "NotValidated", "ace": -8.217, "systemimbalance": -24.415, "alpha": 0.0, "alpha_prime": 0.0, "marginalincrementalprice": 93.545, "marginaldecrementalprice": 78.912, "imbalanceprice": 93.545}, {"datetime": "2025-11-23T01:32:00+00:00", "resolutioncode": "PT1M", "quarterhour": "2025-11-23T01:30:00+00:00", "qualitystatus": "NotValidated", "ace": -12.567, "systemimbalance": -30.847, "alpha": 0.0, "alpha_prime": 0.0, "marginalincrementalprice": 95.09, "marginaldecrementalprice": 92.0, "imbalanceprice": 95.09}, {"datetime": "2025-11-23T01:33:00+00:00", "resolutioncode": "PT1M", "quarterhour": "2025-11-23T01:30:00+00:00", "qualitystatus": "NotValidated", "ace": -13.409, "systemimbalance": -19.571, "alpha": 0.0, "alpha_prime": 0.0, "marginalincrementalprice": 93.545, "marginaldecrementalprice": 92.0, "imbalanceprice": 93.545}, {"datetime": "2025-11-23T01:34:00+00:00", "resolutioncode": "PT1M", "quarterhour": "2025-11-23T01:30:00+00:00", "qualitystatus": "NotValidated", "ace": -16.998, "systemimbalance": -16.007, "alpha": 0.0, "alpha_prime": 0.0, "marginalincrementalprice": 93.545, "marginaldecrementalprice": 92.0, "imbalanceprice": 93.545}, {"datetime": "2025-11-23T01:35:00+00:00", "resolutioncode": "PT1M", "quarterhour": "2025-11-23T01:30:00+00:00", "qualitystatus": "NotValidated", "ace": -20.979, "systemimbalance": -11.07, "alpha": 0.0, "alpha_prime": 0.0, "marginalincrementalprice": 93.545, "marginaldecrementalprice": 92.0, "imbalanceprice": 93.545}, {"datetime": "2025-11-23T01:36:00+00:00", "resolutioncode": "PT1M", "quarterhour": "2025-11-23T01:30:00+00:00", "qualitystatus": "NotValidated", "ace": -24.572, "systemimbalance": -7.391, "alpha": 0.0, "alpha_prime": 0.0, "marginalincrementalprice": 93.545, "marginaldecrementalprice": 92.0, "imbalanceprice": 93.545}, {"datetime": "2025-11-23T01:37:00+00:00", "resolutioncode": "PT1M", "quarterhour": "2025-11-23T01:30:00+00:00", "qualitystatus": "NotValidated", "ace": -24.388, "systemimbalance": -2.851, "alpha": 0.0, "alpha_prime": 0.0, "marginalincrementalprice": 93.545, "marginaldecrementalprice": 92.0, "imbalanceprice": 93.545}, {"datetime": "2025-11-23T01:38:00+00:00", "resolutioncode": "PT1M", "quarterhour": "2025-11-23T01:30:00+00:00", "qualitystatus": "NotValidated", "ace": -22.7, "systemimbalance": -3.199, "alpha": 0.0, "alpha_prime": 0.0, "marginalincrementalprice": 93.545, "marginaldecrementalprice": 92.0, "imbalanceprice": 93.545}, {"datetime": "2025-11-23T01:39:00+00:00", "resolutioncode": "PT1M", "quarterhour": "2025-11-23T01:30:00+00:00", "qualitystatus": "NotValidated", "ace": -20.413, "systemimbalance": 2.773, "alpha": 0.0, "alpha_prime": 0.0, "marginalincrementalprice": 104.115, "marginaldecrementalprice": 93.545, "imbalanceprice": 93.545}, {"datetime": "2025-11-23T01:40:00+00:00", "resolutioncode": "PT1M", "quarterhour": "2025-11-23T01:30:00+00:00", "qualitystatus": "NotValidated", "ace": -18.522, "systemimbalance": 7.78, "alpha": 0.0, "alpha_prime": 0.0, "marginalincrementalprice": 99.951, "marginaldecrementalprice": 93.545, "imbalanceprice": 93.545}, {"datetime": "2025-11-23T01:41:00+00:00", "resolutioncode": "PT1M", "quarterhour": "2025-11-23T01:30:00+00:00", "qualitystatus": "NotValidated", "ace": -15.546, "systemimbalance": 13.659, "alpha": 0.0, "alpha_prime": 0.0, "marginalincrementalprice": 95.09, "marginaldecrementalprice": 93.545, "imbalanceprice": 93.545}, {"datetime": "2025-11-23T01:42:00+00:00", "resolutioncode": "PT1M", "quarterhour": "2025-11-23T01:30:00+00:00", "qualitystatus": "NotValidated", "ace": -13.214, "systemimbalance": 16.36, "alpha": 0.0, "alpha_prime": 0.0, "marginalincrementalprice": 95.09, "marginaldecrementalprice": 93.545, "imbalanceprice": 93.545}, {"datetime": "2025-11-23T01:43:00+00:00", "resolutioncode": "PT1M", "quarterhour": "2025-11-23T01:30:00+00:00", "qualitystatus": "NotValidated", "ace": -10.644, "systemimbalance": 22.952, "alpha": 0.0, "alpha_prime": 0.0, "marginalincrementalprice": 95.09, "marginaldecrementalprice": 93.545, "imbalanceprice": 93.545}, {"datetime": "2025-11-23T01:44:00+00:00", "resolutioncode": "PT1M", "quarterhour": "2025-11-23T01:30:00+00:00", "qualitystatus": "NotValidated", "ace": -9.618, "systemimbalance": 27.44, "alpha": 0.0, "alpha_prime": 0.0, "marginalincrementalprice": 95.09, "marginaldecrementalprice": 83.92, "imbalanceprice": 83.92}, {"datetime": "2025-11-23T01:45:00+00:00", "resolutioncode": "PT1M", "quarterhour": "2025-11-23T01:45:00+00:00", "qualitystatus": "DataIssue", "ace": 5.934, "systemimbalance": 22.549, "alpha": 0.0, "alpha_prime": 0.0, "marginalincrementalprice": 94.9, "marginaldecrementalprice": 94.45, "imbalanceprice": 94.45}, {"datetime": "2025-11-23T01:46:00+00:00", "resolutioncode": "PT1M", "quarterhour": "2025-11-23T01:45:00+00:00", "qualitystatus": "NotValidated", "ace": 2.517, "systemimbalance": -3.807, "alpha": 0.0, "alpha_prime": 0.0, "marginalincrementalprice": 94.45, "marginaldecrementalprice": 90.711, "imbalanceprice": 94.45}, {"datetime": "2025-11-23T01:47:00+00:00", "resolutioncode": "PT1M", "quarterhour": "2025-11-23T01:45:00+00:00", "qualitystatus": "NotValidated", "ace": 0.397, "systemimbalance": -2.948, "alpha": 0.0, "alpha_prime": 0.0, "marginalincrementalprice": 94.45, "marginaldecrementalprice": 92.89, "imbalanceprice": 94.45}, {"datetime": "2025-11-23T01:48:00+00:00", "resolutioncode": "PT1M", "quarterhour": "2025-11-23T01:45:00+00:00", "qualitystatus": "NotValidated", "ace": -0.963, "systemimbalance": -2.685, "alpha": 0.0, "alpha_prime": 0.0, "marginalincrementalprice": 94.45, "marginaldecrementalprice": 90.588, "imbalanceprice": 94.45}, {"datetime": "2025-11-23T01:49:00+00:00", "resolutioncode": "PT1M", "quarterhour": "2025-11-23T01:45:00+00:00", "qualitystatus": "NotValidated", "ace": 0.44, "systemimbalance": -0.614, "alpha": 0.0, "alpha_prime": 0.0, "marginalincrementalprice": 94.45, "marginaldecrementalprice": 85.061, "imbalanceprice": 94.45}, {"datetime": "2025-11-23T01:50:00+00:00", "resolutioncode": "PT1M", "quarterhour": "2025-11-23T01:45:00+00:00", "qualitystatus": "NotValidated", "ace": -0.674, "systemimbalance": -3.926, "alpha": 0.0, "alpha_prime": 0.0, "marginalincrementalprice": 94.45, "marginaldecrementalprice": 85.485, "imbalanceprice": 94.45}, {"datetime": "2025-11-23T01:51:00+00:00", "resolutioncode": "PT1M", "quarterhour": "2025-11-23T01:45:00+00:00", "qualitystatus": "NotValidated", "ace": -2.141, "systemimbalance": -6.925, "alpha": 0.0, "alpha_prime": 0.0, "marginalincrementalprice": 94.45, "marginaldecrementalprice": 85.491, "imbalanceprice": 94.45}, {"datetime": "2025-11-23T01:52:00+00:00", "resolutioncode": "PT1M", "quarterhour": "2025-11-23T01:45:00+00:00", "qualitystatus": "NotValidated", "ace": -1.662, "systemimbalance": -3.11, "alpha": 0.0, "alpha_prime": 0.0, "marginalincrementalprice": 94.45, "marginaldecrementalprice": 78.372, "imbalanceprice": 94.45}, {"datetime": "2025-11-23T01:53:00+00:00", "resolutioncode": "PT1M", "quarterhour": "2025-11-23T01:45:00+00:00", "qualitystatus": "NotValidated", "ace": -0.31, "systemimbalance": -4.674, "alpha": 0.0, "alpha_prime": 0.0, "marginalincrementalprice": 94.45, "marginaldecrementalprice": 75.038, "imbalanceprice": 94.45}, {"datetime": "2025-11-23T01:54:00+00:00", "resolutioncode": "PT1M", "quarterhour": "2025-11-23T01:45:00+00:00", "qualitystatus": "NotValidated", "ace": 0.109, "systemimbalance": -5.274, "alpha": 0.0, "alpha_prime": 0.0, "marginalincrementalprice": 94.45, "marginaldecrementalprice": 73.755, "imbalanceprice": 94.45}, {"datetime": "2025-11-23T01:55:00+00:00", "resolutioncode": "PT1M", "quarterhour": "2025-11-23T01:45:00+00:00", "qualitystatus": "NotValidated", "ace": 0.647, "systemimbalance": -5.698, "alpha": 0.0, "alpha_prime": 0.0, "marginalincrementalprice": 94.45, "marginaldecrementalprice": 72.603, "imbalanceprice": 94.45}, {"datetime": "2025-11-23T01:56:00+00:00", "resolutioncode": "PT1M", "quarterhour": "2025-11-23T01:45:00+00:00", "qualitystatus": "NotValidated", "ace": 0.244, "systemimbalance": 0.275, "alpha": 0.0, "alpha_prime": 0.0, "marginalincrementalprice": 94.9, "marginaldecrementalprice": 94.45, "imbalanceprice": 94.45}, {"datetime": "2025-11-23T01:57:00+00:00", "resolutioncode": "PT1M", "quarterhour": "2025-11-23T01:45:00+00:00", "qualitystatus": "NotValidated", "ace": -0.169, "systemimbalance": 4.498, "alpha": 0.0, "alpha_prime": 0.0, "marginalincrementalprice": 94.9, "marginaldecrementalprice": 94.45, "imbalanceprice": 94.45}, {"datetime": "2025-11-23T01:58:00+00:00", "resolutioncode": "PT1M", "quarterhour": "2025-11-23T01:45:00+00:00", "qualitystatus": "NotValidated", "ace": 0.776, "systemimbalance": 7.292, "alpha": 0.0, "alpha_prime": 0.0, "marginalincrementalprice": 94.9, "marginaldecrementalprice": 94.45, "imbalanceprice": 94.45}]}